BlueBrain/AITONeuralNetwork.py
BlueBrain/NeuralNetwork.py
BlueBrain/__init__.py
BlueBrain-0.2.0.dist-info/METADATA
BlueBrain-0.2.0.dist-info/WHEEL
BlueBrain-0.2.0.dist-info/top_level.txt
BlueBrain-0.2.0.dist-info/RECORD
