Metadata-Version: 2.1
Name: BlueBrain
Version: 0.2.0
Summary: Special AI/ML library for autonomous vehicles and underwater systems
Home-page: UNKNOWN
Author: Uranyum (Mustafa Gülsoy)
Author-email: <mustafagulsoy05@gmail.com>
License: UNKNOWN
Keywords: python,AI,ML,BlueBrain,Self-Drive
Platform: UNKNOWN
Classifier: Development Status :: 2 - Pre-Alpha
Classifier: Intended Audience :: Developers
Classifier: Programming Language :: Python :: 3
Classifier: Operating System :: Unix
Classifier: Operating System :: MacOS :: MacOS X
Classifier: Operating System :: Microsoft :: Windows
Requires-Dist: pickleshare (==0.7.5)
